{
  "round": "Round 1",
  "mas_name": "AG2",
  "benchmark_name": "GSM-Plus",
  "trace_id": 2,
  "trace": "{\n    \"instance_id\": \"02da9c1f-7c36-5739-b723-33a7d4f8e7e7\",\n    \"problem_statement\": [\n        \"Monica is wrapping Christmas gifts. She has 6 gifts to wrap for her family, 4 gifts to wrap for her friends and 2 gifts to wrap for her teachers. She wants to make a bow for each gift. How many inches of ribbon can she use for each gift bow?\"\n    ],\n    \"other_data\": {\n        \"correct\": true,\n        \"answer\": \"None\",\n        \"given\": \"\\\\text{\\\"Data insufficient to solve the problem\\\"}\",\n        \"perturbation_type\": \"critical thinking\",\n        \"seed_question\": \"Monica is wrapping Christmas gifts. She has 6 gifts to wrap for her family, 4 gifts to wrap for her friends and 2 gifts to wrap for her teachers. She has 144 inches of ribbon and wants to make a bow for each gift with it. How many inches of ribbon can she use for each gift bow?\",\n        \"seed_solution\": \"Monica is has 6 gifts for family + 4 gifts for friends + 2 gifts for teachers = <<6+4+2=12>>12 gifts to wrap.\\nHer ribbon can be divided equally 144 inches of ribbon / 12 gifts = <<144/12=12>>12 inches of ribbon per gift.\\n#### 12\",\n        \"seed_answer\": \"12\"\n    },\n    \"trajectory\": [\n        {\n            \"content\": [\n                \"Let's use Python to solve a math problem.\",\n                \"\",\n                \"Query requirements:\",\n                \"You should always use the 'print' function for the output and use fractions/radical forms instead of decimals.\",\n                \"You can use packages like sympy to help you.\",\n                \"You must follow the formats below to write your code:\",\n                \"```python\",\n                \"# your code\",\n                \"```\",\n                \"\",\n                \"First state the key idea to solve the problem. You may choose from three ways to solve the problem:\",\n                \"Case 1: If the problem can be solved with Python code directly, please write a program to solve it. You can enumerate all possible arrangements if needed.\",\n                \"Case 2: If the problem is mostly reasoning, you can solve it by yourself directly.\",\n                \"Case 3: If the problem cannot be handled in the above two ways, please follow this process:\",\n                \"1. Solve the problem step by step (do not over-divide the steps).\",\n                \"2. Take out any queries that can be asked through Python (for example, any calculations or equations that can be calculated).\",\n                \"3. Wait for me to give the results.\",\n                \"4. Continue if you think the result is correct. If the result is invalid or unexpected, please correct your query or reasoning.\",\n                \"\",\n                \"After all the queries are run and you get the answer, put the answer in \\\\boxed{}.\",\n                \"\",\n                \"Problem:\",\n                \"Monica is wrapping Christmas gifts. She has 6 gifts to wrap for her family, 4 gifts to wrap for her friends and 2 gifts to wrap for her teachers. She wants to make a bow for each gift. How many inches of ribbon can she use for each gift bow?\"\n            ],\n            \"role\": \"assistant\",\n            \"name\": \"mathproxyagent\"\n        },\n        {\n            \"content\": [\n                \"This problem is a reasoning problem. The information provided in the problem statement does not give any specifics about the amount of ribbon Monica has or the size of the gift bows. Therefore, this problem cannot be solved with the information provided. More context or information is needed, such as \\\"Monica has 120 inches of ribbon\\\" or \\\"Each bow uses X inches of ribbon\\\".\"\n            ],\n            \"role\": \"user\",\n            \"name\": \"assistant\"\n        },\n        {\n            \"content\": [\n                \"Continue. Please keep solving the problem until you need to query. (If you get to the answer, put it in \\\\boxed{}.)\"\n            ],\n            \"role\": \"assistant\",\n            \"name\": \"mathproxyagent\"\n        },\n        {\n            \"content\": [\n                \"In the current problem, I don't have enough information to solve the problem. If I were to ask you the relevant missing information now, it would be:\",\n                \"1. What is the total length of the ribbon that Monica has?\",\n                \"or\",\n                \"2. How many inches of ribbon does Monica use for each gift bow?\",\n                \"\",\n                \"Could you please provide either of this information so that I could solve the problem? Without any of these pieces of information, the problem remains unsolvable.\"\n            ],\n            \"role\": \"user\",\n            \"name\": \"assistant\"\n        },\n        {\n            \"content\": [\n                \"Continue. Please keep solving the problem until you need to query. (If you get to the answer, put it in \\\\boxed{}.)\"\n            ],\n            \"role\": \"assistant\",\n            \"name\": \"mathproxyagent\"\n        },\n        {\n            \"content\": [\n                \"I'm sorry, but I really need more information to solve this problem. It can't be solved with current data.\"\n            ],\n            \"role\": \"user\",\n            \"name\": \"assistant\"\n        },\n        {\n            \"content\": [\n                \"Continue. Please keep solving the problem until you need to query. (If you get to the answer, put it in \\\\boxed{}.)\"\n            ],\n            \"role\": \"assistant\",\n            \"name\": \"mathproxyagent\"\n        },\n        {\n            \"content\": [\n                \"Based on the current information provided, we cannot continue to effectively solve the problem. Some crucial data is missing. Specifically, we need to know the total length of ribbon that Monica has and/or how many inches of ribbon she uses for each bow. Without such specific information, any attempt to solve the question would be based on assumptions, not facts. Therefore, we sincerely request you to provide the missing information for us to continue with the calculation and eventually find the solution.\"\n            ],\n            \"role\": \"user\",\n            \"name\": \"assistant\"\n        },\n        {\n            \"content\": [\n                \"Continue. Please keep solving the problem until you need to query. (If you get to the answer, put it in \\\\boxed{}.)\"\n            ],\n            \"role\": \"assistant\",\n            \"name\": \"mathproxyagent\"\n        },\n        {\n            \"content\": [\n                \"Since the problem does not provide any specific details of the length of ribbon available to Monica or the amount of ribbon used for each bow, the problem cannot be solved. Therefore, there is no solution. So, we can say the problem is unsolved. \\\\boxed{\\\\text{\\\"Data insufficient to solve the problem\\\"}}.\"\n            ],\n            \"role\": \"user\",\n            \"name\": \"assistant\"\n        }\n    ],\n    \"note\": {\n        \"text\": [\n            \"The solution is correct. The mathproxyagent keeps asking to continue even if it was clear that the problem was unsolvable. \"\n        ],\n        \"options\": {\n            \"Fail to detect ambiguities/contradictions\": \"no\",\n            \"Proceed with incorrect assumptions\": \"no\",\n            \"Fail to elicit clarification\": \"no\",\n            \"Tendency to overachieve\": \"no\",\n            \"Underperform by waiting on instructions\": \"no\",\n            \"Withholding relevant information\": \"no\",\n            \"Derailing from task objectives\": \"no\",\n            \"Waiting on agents to discover known insights for increased confidence\": \"no\",\n            \"Redundant conversation turns for iterative tasks rather than batching\": \"no\",\n            \"Unaware of stopping conditions\": \"yes\",\n            \"Difficulty in agreeing with agents\": \"no\",\n            \"No attempt to verify outcome\": \"no\",\n            \"Evaluator agent fails to be critical\": \"no\",\n            \"Poor adherence to specified constraints\": \"no\",\n            \"Misalignment between internal thoughts and response message\": \"no\",\n            \"Claiming that a task is done while it is not true.\": \"no\",\n            \"Ignoring good suggestions from other agent\": \"yes\",\n            \"Discontinued reasoning\": \"no\",\n            \"Trajectory restart\": \"no\",\n            \"Step repetition\": \"no\",\n            \"Invented content\": \"no\",\n            \"Blurring roles\": \"no\"\n        }\n    }\n}",
  "annotations": [
    {
      "failure mode": "1.1 Poor task constraint compliance\n\nFailure to adhere to the specified constraints or requirements of a given task, leading to suboptimal or incorrect outcomes.",
      "annotator_1": false,
      "annotator_2": false,
      "annotator_3": false
    },
    {
      "failure mode": "1.2 Inconsistency between reasoning and action\n\nDiscrepancy between the logical reasoning process and the actual actions taken by the agent, potentially resulting in unexpected or undesired behaviors.",
      "annotator_1": false,
      "annotator_2": false,
      "annotator_3": false
    },
    {
      "failure mode": "1.3 Undetected conversation ambiguities and contradictions\n\nFailure to recognize unclear or conflicting information within the dialogue, leading to misunderstandings or erroneous conclusions.",
      "annotator_1": false,
      "annotator_2": false,
      "annotator_3": false
    },
    {
      "failure mode": "1.4 Fail to elicit clarification\n(between agents)\nInability to request additional information between agent when faced with unclear or incomplete data, potentially resulting in incorrect actions.",
      "annotator_1": false,
      "annotator_2": false,
      "annotator_3": false
    },
    {
      "failure mode": "1.5 Unaware of stopping conditions\n\nLack of recognition or understanding of the criteria that should trigger the termination of the agents’ interaction, potentially leading to unnecessary continuation.",
      "annotator_1": true,
      "annotator_2": true,
      "annotator_3": true
    },
    {
      "failure mode": "2.1 Unbatched repetitive execution\n\nInefficient repetition of tasks that could be more effectively grouped and executed together, leading to increased processing time and resource consumption.",
      "annotator_1": false,
      "annotator_2": false,
      "annotator_3": false
    },
    {
      "failure mode": "2.2 Step repetition\n\nUnnecessary reiteration of previously completed steps in a process, potentially causing delays or errors in task completion.",
      "annotator_1": false,
      "annotator_2": false,
      "annotator_3": false
    },
    {
      "failure mode": "2.3 Backtracking interruption\n\nUnexpected context truncation, disregarding recent interaction history and reverting to an antecedent conversational state.",
      "annotator_1": false,
      "annotator_2": false,
      "annotator_3": false
    },
    {
      "failure mode": "2.4 Conversation reset \n\nUnexpected or unwarranted restarting of a dialogue, potentially losing context and progress made in the interaction.",
      "annotator_1": false,
      "annotator_2": false,
      "annotator_3": false
    },
    {
      "failure mode": "2.5 Derailment from task\n\nDeviation from the intended objective or focus of a given task, potentially resulting in irrelevant or unproductive actions.",
      "annotator_1": false,
      "annotator_2": false,
      "annotator_3": false
    },
    {
      "failure mode": "2.6 Disobey role specification\n\nFailure to adhere to the defined responsibilities and constraints of an assigned role, potentially leading to an agent behaving like another.",
      "annotator_1": false,
      "annotator_2": false,
      "annotator_3": false
    },
    {
      "failure mode": "3.1 Disagreement induced inaction\n\nPersistent inability of agents to converge on a mutually acceptable resolution or collaborative course of action.",
      "annotator_1": false,
      "annotator_2": false,
      "annotator_3": false
    },
    {
      "failure mode": "3.2 Withholding relevant information\n\nFailure to share or communicate important data that an agent has obtained before and did not share that information with other agents potentially leading to failures or inefficiencies. ",
      "annotator_1": false,
      "annotator_2": false,
      "annotator_3": false
    },
    {
      "failure mode": "3.3 Ignoring suggestions from agents\n\nDisregarding or failing to adequately consider input or recommendations provided by other agents in the system, potentially leading to suboptimal decisions or missed opportunities for collaboration.",
      "annotator_1": true,
      "annotator_2": true,
      "annotator_3": true
    },
    {
      "failure mode": "3.4 Waiting for known information\n\nInefficient idling or delay in task execution while waiting for or requiring information that is already available, leading to unnecessary latency in system performance, or failure to execute the task.\nTere is a case where it is different to holding information",
      "annotator_1": false,
      "annotator_2": false,
      "annotator_3": false
    },
    {
      "failure mode": "4.1 Ill specified termination condition leading to premature termination\n\nEnding a dialogue, interaction or task before all necessary information has been exchanged or objectives have been met. Necessary information constitutes verification of outputs, key data (e.g. api tokens) etc. that are necessary for the success of the task, and agents could have obtained if they tried more or already obtained but failed to communicate to other agents before termination.",
      "annotator_1": false,
      "annotator_2": false,
      "annotator_3": false
    },
    {
      "failure mode": "4.3 Lack of critical verification\n(system designed to but agents didn't)\n\n- \n\n- robustness (it covers also edge cases) \n- error handling etc.\n(broader)\n\nFailure to adequately validate or cross-check crucial information or decisions during the iterations, potentially leading to errors or vulnerabilities in the system.\n\n1. verifier exists in the system, but it is weak or badly design\n2. the system attempts to verify, but doesn't cover all aspects of the design to make a strong output",
      "annotator_1": false,
      "annotator_2": false,
      "annotator_3": false
    },
    {
      "failure mode": "4.2 Lack of result verification\n(no explicit design, only when the system benefits really ) \nOmission of proper checking or confirmation of task outcomes or system outputs, potentially allowing errors or inconsistencies to propagate undetected.\n\nNEW: FUNCTION CORRECTNESS here\n\n1. no verification in MAS \n2. verification is designed to exist in MAS, but verifier fail to complete what was exactly prompted to do. Eg: make sure the code compiles, but the code doesn't even compile",
      "annotator_1": false,
      "annotator_2": false,
      "annotator_3": false
    }
  ]
}